{
  "records": [
    {
      "name": "Account Switch",
      "created_at": "2026-01-29 10:34:14",
      "actions": [
        {
          "type": "key",
          "delay": 0.0,
          "key": "esc"
        },
        {
          "type": "click",
          "delay": 2.074,
          "x": "1716",
          "y": "851",
          "button": "left"
        },
        {
          "type": "click",
          "delay": 0.124,
          "x": "1716",
          "y": "851",
          "button": "left"
        },
        {
          "type": "click",
          "delay": 1.673,
          "x": "1875",
          "y": "809",
          "button": "left"
        },
        {
          "type": "click",
          "delay": 0.161,
          "x": "1875",
          "y": "809",
          "button": "left"
        },
        {
          "type": "key",
          "delay": 5.118,
          "key": "delete"
        },
        {
          "type": "key",
          "delay": 0.65,
          "key": "g"
        },
        {
          "type": "key",
          "delay": 0.22,
          "key": "i"
        },
        {
          "type": "key",
          "delay": 0.1,
          "key": "a"
        },
        {
          "type": "key",
          "delay": 0.16,
          "key": "c"
        },
        {
          "type": "key",
          "delay": 0.12,
          "key": "o"
        },
        {
          "type": "key",
          "delay": 0.18,
          "key": "m"
        },
        {
          "type": "key",
          "delay": 0.1,
          "key": "o"
        },
        {
          "type": "key",
          "delay": 0.38,
          "key": "."
        },
        {
          "type": "key",
          "delay": 0.51,
          "key": "j"
        },
        {
          "type": "key",
          "delay": 0.78,
          "key": "o"
        },
        {
          "type": "key",
          "delay": 0.42,
          "key": "g"
        },
        {
          "type": "key",
          "delay": 0.22,
          "key": "h"
        },
        {
          "type": "key",
          "delay": 0.21,
          "key": "u"
        },
        {
          "type": "key",
          "delay": 0.52,
          "key": "r"
        },
        {
          "type": "key",
          "delay": 0.19,
          "key": "t"
        },
        {
          "type": "key",
          "delay": 0.46,
          "key": "ctrl_l"
        },
        {
          "type": "key",
          "delay": 0.001,
          "key": "alt_gr"
        },
        {
          "type": "key",
          "delay": 0.319,
          "key": "@"
        },
        {
          "type": "key",
          "delay": 0.62,
          "key": "w"
        },
        {
          "type": "key",
          "delay": 0.24,
          "key": "e"
        },
        {
          "type": "key",
          "delay": 0.31,
          "key": "b"
        },
        {
          "type": "key",
          "delay": 0.43,
          "key": "."
        },
        {
          "type": "key",
          "delay": 0.17,
          "key": "d"
        },
        {
          "type": "key",
          "delay": 0.22,
          "key": "e"
        },
        {
          "type": "key",
          "delay": 0.26,
          "key": "shift"
        },
        {
          "type": "key",
          "delay": 1.09,
          "key": "tab"
        },
        {
          "type": "key",
          "delay": 0.37,
          "key": "shift"
        },
        {
          "type": "key",
          "delay": 0.46,
          "key": "U"
        },
        {
          "type": "key",
          "delay": 0.23,
          "key": "n"
        },
        {
          "type": "key",
          "delay": 0.17,
          "key": "i"
        },
        {
          "type": "key",
          "delay": 0.2,
          "key": "v"
        },
        {
          "type": "key",
          "delay": 0.19,
          "key": "e"
        },
        {
          "type": "key",
          "delay": 0.23,
          "key": "r"
        },
        {
          "type": "key",
          "delay": 0.29,
          "key": "s"
        },
        {
          "type": "key",
          "delay": 0.26,
          "key": "a"
        },
        {
          "type": "key",
          "delay": 0.32,
          "key": "l"
        },
        {
          "type": "key",
          "delay": 0.36,
          "key": "1"
        },
        {
          "type": "key",
          "delay": 0.31,
          "key": "2"
        },
        {
          "type": "key",
          "delay": 0.35,
          "key": "3"
        },
        {
          "type": "key",
          "delay": 0.23,
          "key": "shift"
        },
        {
          "type": "key",
          "delay": 0.16,
          "key": "*"
        },
        {
          "type": "key",
          "delay": 3.3,
          "key": "enter"
        }
      ]
    }
  ]
}